Workbook

Sheet 明细
A1: 大区 | B1: 组别 | C1: 客服 | D1: 账户名称 | E1: 公司名称 | F1: 开户日期 | G1: 网站名称 | H1: 网站URL | I1: 8月总消费 | J1: 有消费天数 | K1: 户均消费 | L1: 户均完成率 | M1: 搜索点击消费20230801 | N1: 搜索点击消费20230802 | O1: 搜索点击消费20230803 | P1: 搜索点击消费20230804 | Q1: 搜索点击消费20230805 | R1: 搜索点击消费20230806 | S1: 搜索点击消费20230807 | T1: 搜索点击消费20230808 | U1: 搜索点击消费20230809 | V1: 搜索点击消费20230810 | W1: 搜索点击消费20230811 | X1: 搜索点击消费20230812 | Y1: 搜索点击消费20230813 | Z1: 搜索点击消费20230814 | AA1: 搜索点击消费20230815 | AB1: 搜索点击消费20230816 | AC1: 搜索点击消费20230817 | AD1: 搜索点击消费20230818 | AE1: 搜索点击消费20230819 | AF1: 搜索点击消费20230820 | AG1: 搜索点击消费20230821 | AH1: 搜索点击消费20230822 | AI1: 搜索点击消费20230823 | AJ1: 搜索点击消费20230824 | AK1: 搜索点击消费20230825 | AL1: 搜索点击消费20230826 | AM1: 搜索点击消费20230827 | AN1: 搜索点击消费20230828 | AO1: 搜索点击消费20230829 | AP1: 搜索点击消费20230830 | AQ1: 搜索点击消费20230831
A2: 漳州客服部 | B2: 漳州新开 | C2: 陈俊华 | D2: 百佳园艺场 | E2: 漳浦县马口百佳园艺场 | F2: 42706.612 | G2: 漳浦县马口百佳园艺场 | H2: http://www.mkbjyyc.com/ | I2: 0 | J2: 0 | K2: 0 | L2: 0 | M2: 0 | N2: 0 | O2: 0 | P2: 0 | Q2: 0 | R2: 0 | S2: 0 | T2: 0 | U2: 0 | V2: 0 | W2: 0 | X2: 0 | Y2: 0 | Z2: 0
A3: 泉州中小企业增值部 | B3: 泉州新开 | C3: 傅佳玲 | D3: 福建元辉 | E3: 福建省元辉消防科技有限公司 | F3: 45112.648 | G3: 福建省元辉消防科技有限公司 | H3: http://qianhu.wejianzhan.com | I3: 1563.84 | J3: 14 | K3: 111.70286 | L3: 2.2340571 | M3: 142.13 | N3: 114.42 | O3: 110.51 | P3: 100.75 | Q3: 115.81 | R3: 46.6 | S3: 120.37 | T3: 142.48 | U3: 52.46 | V3: 107.26 | W3: 106.35 | X3: 117.97 | Y3: 151.33 | Z3: 135.4
A4: 漳州客服部 | B4: 漳州新开 | C4: 陈俊华 | D4: 盛兴丰田 | E4: 漳州盛兴丰田汽车销售服务有限公司 | F4: 42122.675 | G4: 漳州盛兴丰田汽车销售服务有限公司 | H4: http://zzsxtoyota.com | I4: 0 | J4: 0 | K4: 0 | L4: 0 | M4: 0 | N4: 0 | O4: 0 | P4: 0 | Q4: 0 | R4: 0 | S4: 0 | T4: 0 | U4: 0 | V4: 0 | W4: 0 | X4: 0 | Y4: 0 | Z4: 0
A5: 漳州客服部 | B5: 漳州新开 | C5: 陈俊华 | D5: 润彤化工 | E5: 漳州市润彤化工有限公司 | F5: 41400.484 | G5: 漳州市润彤化工有限公司 | H5: http://www.zgrt999.com | I5: 0 | J5: 0 | K5: 0 | L5: 0 | M5: 0 | N5: 0 | O5: 0 | P5: 0 | Q5: 0 | R5: 0 | S5: 0 | T5: 0 | U5: 0 | V5: 0 | W5: 0 | X5: 0 | Y5: 0 | Z5: 0
A6: 泉州中小企业增值部 | B6: 泉州新开 | C6: 吴燕红 | D6: 唤我 | E6: 泉州唤我电子商务有限公司 | F6: 0 | G6: 泉州唤我电子商务有限公司 | H6: http://qianhu.wejianzhan.com | I6: 0 | J6: 0 | K6: 0 | L6: 0 | M6: 0 | N6: 0 | O6: 0 | P6: 0 | Q6: 0 | R6: 0 | S6: 0 | T6: 0 | U6: 0 | V6: 0 | W6: 0 | X6: 0 | Y6: 0 | Z6: 0
A7: 新开部门 | B7: 新开二部 | C7: 林华卿 | D7: 中闽电子 | E7: 中闽在线（厦门）电子商务有限公司 | F7: 45140.399 | G7: 中闽在线（厦门）电子商务有限公司 | H7: http://qicai.zhongminzaixian.com | I7: 1146.96 | J7: 9 | K7: 127.44 | L7: 1.8205714 | M7: 0 | N7: 0 | O7: 0 | P7: 178.33 | Q7: 0 | R7: 0 | S7: 37.42 | T7: 75.31 | U7: 115 | V7: 137.24 | W7: 67.87 | X7: 129.25 | Y7: 78.5 | Z7: 328.04
A8: 泉州中小企业增值部 | B8: 泉州新开 | C8: 吴燕红 | D8: 望大科技 | E8: 厦门望大科技有限公司 | F8: 0 | G8: 厦门望大科技有限公司 | H8: http://www.12909.com/ | I8: 0 | J8: 0 | K8: 0 | L8: 0 | M8: 0 | N8: 0 | O8: 0 | P8: 0 | Q8: 0 | R8: 0 | S8: 0 | T8: 0 | U8: 0 | V8: 0 | W8: 0 | X8: 0 | Y8: 0 | Z8: 0
A9: 漳州客服部 | B9: 漳州新开 | C9: 陈俊华 | D9: 参天企业 | E9: 漳州市参天企业管理有限公司 | F9: 44694.691 | G9: 漳州市参天企业管理有限公司 | H9: http://qianhu.wejianzhan.com | I9: 0 | J9: 0 | K9: 0 | L9: 0 | M9: 0 | N9: 0 | O9: 0 | P9: 0 | Q9: 0 | R9: 0 | S9: 0 | T9: 0 | U9: 0 | V9: 0 | W9: 0 | X9: 0 | Y9: 0 | Z9: 0
A10: 泉州中小企业增值部 | B10: 泉州新开 | C10: 王凤钦 | D10: 泉州龙人1 | E10: 南安市龙人伍心家园福利养老院 | F10: 44855.595 | G10: 南安市龙人伍心家园福利养老院 | H10: http://qianhu.wejianzhan.com | I10: 0 | J10: 0 | K10: 0 | L10: 0 | M10: 0 | N10: 0 | O10: 0 | P10: 0 | Q10: 0 | R10: 0 | S10: 0 | T10: 0 | U10: 0 | V10: 0 | W10: 0 | X10: 0 | Y10: 0 | Z10: 0
A11: 新开部门 | B11: 新开二部 | C11: 梁烨 | D11: 厦门鲲图 | E11: 厦门鲲图全景摄影有限公司 | F11: 45076.441 | G11: 厦门鲲图全景摄影有限公司 | H11: http://www.shuaiqitz.com | I11: 963.74 | J11: 14 | K11: 68.838571 | L11: 0.98340816 | M11: 82.51 | N11: 61.21 | O11: 100.06 | P11: 101.66 | Q11: 81.74 | R11: 76.64 | S11: 79.34 | T11: 100.59 | U11: 45.87 | V11: 87.26 | W11: 52.82 | X11: 11.52 | Y11: 25.73 | Z11: 56.79
A12: 泉州中小企业增值部 | B12: 泉州新开 | C12: 吴燕红 | D12: 李树芳律师 | E12: 李树芳 | F12: 0 | G12: 李树芳 | H12: http://www.axlishufangls.com | I12: 0 | J12: 0 | K12: 0 | L12: 0 | M12: 0 | N12: 0 | O12: 0 | P12: 0 | Q12: 0 | R12: 0 | S12: 0 | T12: 0 | U12: 0 | V12: 0 | W12: 0 | X12: 0 | Y12: 0 | Z12: 0
A13: 泉州中小企业增值部 | B13: 泉州新开 | C13: 吴燕红 | D13: 闽山消防2 | E13: 福建闽山消防有限公司 | F13: 0 | G13: 福建闽山消防有限公司 | H13: http://qianhu.wejianzhan.com | I13: 0 | J13: 0 | K13: 0 | L13: 0 | M13: 0 | N13: 0 | O13: 0 | P13: 0 | Q13: 0 | R13: 0 | S13: 0 | T13: 0 | U13: 0 | V13: 0 | W13: 0 | X13: 0 | Y13: 0 | Z13: 0
... A2169: 漳州客服部 | B2169: 漳州新开 | C2169: 陈俊华 | D2169: 和健塑料 | E2169: 漳浦和健塑料制品有限公司 | F2169: 42907.49 | G2169: 漳浦和健塑料制品有限公司 | H2169: http://zphjsl.com/ | I2169: 0 | J2169: 0 | K2169: 0 | L2169: 0 | M2169: 0 | N2169: 0 | O2169: 0 | P2169: 0 | Q2169: 0 | R2169: 0 | S2169: 0 | T2169: 0 | U2169: 0 | V2169: 0 | W2169: 0 | X2169: 0 | Y2169: 0 | Z2169: 0

Sheet 各部门完成情况
A1: 部门 | B1: 部别 | C1: 客服 | D1: 有消费客户数 | E1: 达标客户数 | F1: 完成率 | I1: 大区 | J1: 部别 | K1: 有消费客户 | L1: 达标客户数 | M1: 完成率-截止昨天
A2: 新开部门 （户均70） | B2: 新开部门 | C2: 朱惠敏 | D2: =COUNTIFS(明细!$C:$C,各部门完成情况!C2,明细!$I:$I,">0") -> 0 | E2: =COUNTIFS(明细!$C:$C,各部门完成情况!C2,明细!$K:$K,">=70") -> 0 | F2: =IF(D2=0,"0.00%",E2/D2) -> 0.00% | I2: 新开部 | J2: 新开一部 | K2: =COUNTIFS(明细!$B:$B,各部门完成情况!J2,明细!$J:$J,">0") -> 43 | L2: =COUNTIFS(明细!$B:$B,各部门完成情况!J2,明细!$K:$K,">70") -> 34 | M2: =L2/K2 -> 0.79069767
B3: 新开部门 | C3: 建站十分 | D3: =COUNTIFS(明细!$C:$C,各部门完成情况!C3,明细!$I:$I,">0") -> 0 | E3: =COUNTIFS(明细!$C:$C,各部门完成情况!C3,明细!$K:$K,">=70") -> 0 | F3: =IF(D3=0,"0.00%",E3/D3) -> 0.00% | I3: 新开部 | J3: 新开二部 | K3: =COUNTIFS(明细!$B:$B,各部门完成情况!J3,明细!$J:$J,">0") -> 72 | L3: =COUNTIFS(明细!$B:$B,各部门完成情况!J3,明细!$K:$K,">70") -> 48 | M3: =L3/K3 -> 0.66666667
B4: 新开一部 | C4: 叶惠 | D4: =COUNTIFS(明细!$C:$C,各部门完成情况!C4,明细!$I:$I,">0") -> 2 | E4: =COUNTIFS(明细!$C:$C,各部门完成情况!C4,明细!$K:$K,">=70") -> 0 | F4: =IF(D4=0,"0.00%",E4/D4) -> 0 | I4: 泉州部门 | J4: 泉州新开 | K4: =COUNTIFS(明细!$B:$B,各部门完成情况!J4,明细!$J:$J,">0") -> 55 | L4: =COUNTIFS(明细!$B:$B,各部门完成情况!J4,明细!$K:$K,">50") -> 39 | M4: =L4/K4 -> 0.70909091
B5: 新开一部 | C5: 张唯唯 | D5: =COUNTIFS(明细!$C:$C,各部门完成情况!C5,明细!$I:$I,">0") -> 12 | E5: =COUNTIFS(明细!$C:$C,各部门完成情况!C5,明细!$K:$K,">=70") -> 9 | F5: =IF(D5=0,"0.00%",E5/D5) -> 0.75 | I5: 漳州部门 | J5: 漳州新开 | K5: =COUNTIFS(明细!$B:$B,各部门完成情况!J5,明细!$J:$J,">0") -> 34 | L5: =COUNTIFS(明细!$B:$B,各部门完成情况!J5,明细!$K:$K,">50") -> 21 | M5: =L5/K5 -> 0.61764706
B6: 新开一部 | C6: 林雅清 | D6: =COUNTIFS(明细!$C:$C,各部门完成情况!C6,明细!$I:$I,">0") -> 17 | E6: =COUNTIFS(明细!$C:$C,各部门完成情况!C6,明细!$K:$K,">=70") -> 15 | F6: =IF(D6=0,"0.00%",E6/D6) -> 0.88235294
B7: 新开一部 | C7: 蓝淑敏 | D7: =COUNTIFS(明细!$C:$C,各部门完成情况!C7,明细!$I:$I,">0") -> 0 | E7: =COUNTIFS(明细!$C:$C,各部门完成情况!C7,明细!$K:$K,">=70") -> 0 | F7: =IF(D7=0,"0.00%",E7/D7) -> 0.00%
B8: 新开一部 | C8: 林裕芳 | D8: =COUNTIFS(明细!$C:$C,各部门完成情况!C8,明细!$I:$I,">0") -> 12 | E8: =COUNTIFS(明细!$C:$C,各部门完成情况!C8,明细!$K:$K,">=70") -> 10 | F8: =IF(D8=0,"0.00%",E8/D8) -> 0.83333333
B9: 新开二部 | C9: 叶晓欢 | D9: =COUNTIFS(明细!$C:$C,各部门完成情况!C9,明细!$I:$I,">0") -> 1 | E9: =COUNTIFS(明细!$C:$C,各部门完成情况!C9,明细!$K:$K,">=70") -> 0 | F9: =IF(D9=0,"0.00%",E9/D9) -> 0
B10: 新开二部 | C10: 林华卿 | D10: =COUNTIFS(明细!$C:$C,各部门完成情况!C10,明细!$I:$I,">0") -> 15 | E10: =COUNTIFS(明细!$C:$C,各部门完成情况!C10,明细!$K:$K,">=70") -> 10 | F10: =IF(D10=0,"0.00%",E10/D10) -> 0.66666667
B11: 新开二部 | C11: 程秋平 | D11: =COUNTIFS(明细!$C:$C,各部门完成情况!C11,明细!$I:$I,">0") -> 13 | E11: =COUNTIFS(明细!$C:$C,各部门完成情况!C11,明细!$K:$K,">=70") -> 10 | F11: =IF(D11=0,"0.00%",E11/D11) -> 0.76923077
B12: 新开二部 | C12: 梁烨 | D12: =COUNTIFS(明细!$C:$C,各部门完成情况!C12,明细!$I:$I,">0") -> 15 | E12: =COUNTIFS(明细!$C:$C,各部门完成情况!C12,明细!$K:$K,">=70") -> 8 | F12: =IF(D12=0,"0.00%",E12/D12) -> 0.53333333
B13: 新开二部 | C13: 林霖 | D13: =COUNTIFS(明细!$C:$C,各部门完成情况!C13,明细!$I:$I,">0") -> 16 | E13: =COUNTIFS(明细!$C:$C,各部门完成情况!C13,明细!$K:$K,">=70") -> 9 | F13: =IF(D13=0,"0.00%",E13/D13) -> 0.5625
B14: 新开二部 | C14: 童莺莺 | D14: =COUNTIFS(明细!$C:$C,各部门完成情况!C14,明细!$I:$I,">0") -> 12 | E14: =COUNTIFS(明细!$C:$C,各部门完成情况!C14,明细!$K:$K,">=70") -> 11 | F14: =IF(D14=0,"0.00%",E14/D14) -> 0.91666667
A15: 泉州部门 （户均50） | B15: 泉州新开 | C15: 泉州建站 | D15: =COUNTIFS(明细!$C:$C,各部门完成情况!C15,明细!$I:$I,">0") -> 0 | E15: =COUNTIFS(明细!$C:$C,各部门完成情况!C15,明细!$K:$K,">=70") -> 0 | F15: =IF(D15=0,"0.00%",E15/D15) -> 0.00%
B16: 泉州新开 | C16: 吴燕红 | D16: =COUNTIFS(明细!$C:$C,各部门完成情况!C16,明细!$I:$I,">0") -> 3 | E16: =COUNTIFS(明细!$C:$C,各部门完成情况!C16,明细!$K:$K,">=70") -> 1 | F16: =IF(D16=0,"0.00%",E16/D16) -> 0.33333333
B17: 泉州新开 | C17: 王凤钦 | D17: =COUNTIFS(明细!$C:$C,各部门完成情况!C17,明细!$I:$I,">0") -> 16 | E17: =COUNTIFS(明细!$C:$C,各部门完成情况!C17,明细!$K:$K,">=70") -> 7 | F17: =IF(D17=0,"0.00%",E17/D17) -> 0.4375
B18: 泉州新开 | C18: 傅佳玲 | D18: =COUNTIFS(明细!$C:$C,各部门完成情况!C18,明细!$I:$I,">0") -> 16 | E18: =COUNTIFS(明细!$C:$C,各部门完成情况!C18,明细!$K:$K,">=70") -> 9 | F18: =IF(D18=0,"0.00%",E18/D18) -> 0.5625
B19: 泉州新开 | C19: 邱彬彬 | D19: =COUNTIFS(明细!$C:$C,各部门完成情况!C19,明细!$I:$I,">0") -> 20 | E19: =COUNTIFS(明细!$C:$C,各部门完成情况!C19,明细!$K:$K,">=70") -> 10 | F19: =IF(D19=0,"0.00%",E19/D19) -> 0.5
A20: 漳州部门 （户均50） | B20: 漳州新开 | C20: 游惠卿 | D20: =COUNTIFS(明细!$C:$C,各部门完成情况!C20,明细!$I:$I,">0") -> 18 | E20: =COUNTIFS(明细!$C:$C,各部门完成情况!C20,明细!$K:$K,">=70") -> 6 | F20: =IF(D20=0,"0.00%",E20/D20) -> 0.33333333
B21: 漳州新开 | C21: 吴清玉 | D21: =COUNTIFS(明细!$C:$C,各部门完成情况!C21,明细!$I:$I,">0") -> 16 | E21: =COUNTIFS(明细!$C:$C,各部门完成情况!C21,明细!$K:$K,">=70") -> 7 | F21: =IF(D21=0,"0.00%",E21/D21) -> 0.4375
